README.rst
setup.py
inkwave/__init__.py
inkwave/cli.py
inkwave/core.py
inkwave/errors.py
inkwave/helpers.py
inkwave/router.py
inkwave/utils.py
inkwave.egg-info/PKG-INFO
inkwave.egg-info/SOURCES.txt
inkwave.egg-info/dependency_links.txt
inkwave.egg-info/entry_points.txt
inkwave.egg-info/not-zip-safe
inkwave.egg-info/requires.txt
inkwave.egg-info/top_level.txt
inkwave/commands/__init__.py
inkwave/commands/build.py
inkwave/commands/data.py
inkwave/commands/serve.py
inkwave/plugins/__init__.py
inkwave/plugins/jinja.py
inkwave/plugins/json.py
inkwave/plugins/markdown.py
inkwave/plugins/yaml.py
inkwave/plugins/transform/__init__.py
inkwave/plugins/transform/html.py
inkwave/plugins/transform/sass.py
inkwave/tools/__init__.py
inkwave/tools/sass.py