Metadata-Version: 1.1
Name: inkwave
Version: 0.3
Summary: Framework for building static websites
Home-page: http://www.inkwave.org
Author: Boris Kaul
Author-email: me@boriskaul.com
License: UNKNOWN
Download-URL: https://github.com/localvoid/inkwave/tarball/master
Platform: Any
Classifier: Development Status :: 3 - Alpha
Classifier: License :: OSI Approved :: BSD License
Classifier: Programming Language :: Python
Classifier: Programming Language :: Python :: 3
Classifier: Programming Language :: Python :: 3.3
Classifier: Intended Audience :: Developers
Classifier: Environment :: Console
